onnxruntime/LICENSE
onnxruntime/Privacy.md
onnxruntime/Qualcomm_LICENSE.pdf
onnxruntime/ThirdPartyNotices.txt
onnxruntime/__init__.py
onnxruntime/backend/__init__.py
onnxruntime/backend/backend.py
onnxruntime/backend/backend_rep.py
onnxruntime/capi/QnnCpu.dll
onnxruntime/capi/QnnGpu.dll
onnxruntime/capi/QnnHtp.dll
onnxruntime/capi/QnnHtpPrepare.dll
onnxruntime/capi/QnnHtpV73Stub.dll
onnxruntime/capi/QnnSystem.dll
onnxruntime/capi/__init__.py
onnxruntime/capi/_ld_preload.py
onnxruntime/capi/_pybind_state.py
onnxruntime/capi/build_and_package_info.py
onnxruntime/capi/convert_npz_to_onnx_adapter.py
onnxruntime/capi/libQnnHtpV68Skel.so
onnxruntime/capi/libQnnHtpV73Skel.so
onnxruntime/capi/libqnnhtpv73.cat
onnxruntime/capi/onnxruntime.dll
onnxruntime/capi/onnxruntime_collect_build_info.py
onnxruntime/capi/onnxruntime_inference_collection.py
onnxruntime/capi/onnxruntime_providers_qnn.dll
onnxruntime/capi/onnxruntime_providers_shared.dll
onnxruntime/capi/onnxruntime_pybind11_state.pyd
onnxruntime/capi/onnxruntime_validation.py
onnxruntime/capi/version_info.py
onnxruntime/datasets/__init__.py
onnxruntime/datasets/logreg_iris.onnx
onnxruntime/datasets/mul_1.onnx
onnxruntime/datasets/sigmoid.onnx
onnxruntime/quantization/__init__.py
onnxruntime/quantization/base_quantizer.py
onnxruntime/quantization/calibrate.py
onnxruntime/quantization/matmul_bnb4_quantizer.py
onnxruntime/quantization/matmul_nbits_quantizer.py
onnxruntime/quantization/onnx_model.py
onnxruntime/quantization/onnx_quantizer.py
onnxruntime/quantization/preprocess.py
onnxruntime/quantization/qdq_loss_debug.py
onnxruntime/quantization/qdq_quantizer.py
onnxruntime/quantization/quant_utils.py
onnxruntime/quantization/quantize.py
onnxruntime/quantization/registry.py
onnxruntime/quantization/shape_inference.py
onnxruntime/quantization/static_quantize_runner.py
onnxruntime/quantization/tensor_quant_overrides.py
onnxruntime/quantization/CalTableFlatBuffers/KeyValue.py
onnxruntime_qnn-1.23.2.dist-info/METADATA
onnxruntime_qnn-1.23.2.dist-info/WHEEL
onnxruntime_qnn-1.23.2.dist-info/entry_points.txt
onnxruntime_qnn-1.23.2.dist-info/top_level.txt
onnxruntime_qnn-1.23.2.dist-info/RECORD
